main.py
robotrepos-0.1.0.dist-info/METADATA
robotrepos-0.1.0.dist-info/WHEEL
robotrepos-0.1.0.dist-info/entry_points.txt
robotrepos-0.1.0.dist-info/top_level.txt
robotrepos-0.1.0.dist-info/RECORD
