Metadata-Version: 2.4
Name: robotrepos
Version: 0.1.0
Summary: Add your description here
Requires-Python: >=3.11
Requires-Dist: gitpython>=3.1.44
Requires-Dist: httpx>=0.28.1
Requires-Dist: mcp[cli]>=1.7.1
